deck2pdf/__init__.py
deck2pdf/_types.py
deck2pdf/cli.py
deck2pdf/py.typed
deck2pdf/reader.py
deck2pdf/writer.py
deck2pdf/slides/__init__.py
deck2pdf/slides/_base.py
deck2pdf/slides/generic.py
deck2pdf/slides/revealjs.py
deck2pdf-0.9.0.dist-info/METADATA
deck2pdf-0.9.0.dist-info/WHEEL
deck2pdf-0.9.0.dist-info/entry_points.txt
deck2pdf-0.9.0.dist-info/licenses/LICENSE
deck2pdf-0.9.0.dist-info/RECORD
