Metadata-Version: 2.4
Name: deck2pdf
Version: 0.9.0
Summary: Convert from html presentaition to pdf.
Project-URL: Repository, https://github.com/attakei/deck2pdf-python
Author-email: Kazuya Takei <myself@attakei.net>
License: Apache License
License-File: LICENSE
Requires-Python: >=3.8
Requires-Dist: click>=8
Requires-Dist: playwright>=1
Requires-Dist: pypdf>=5
